setup.py
package_test_2298/__init__.py
package_test_2298/help.py
package_test_2298.egg-info/PKG-INFO
package_test_2298.egg-info/SOURCES.txt
package_test_2298.egg-info/dependency_links.txt
package_test_2298.egg-info/top_level.txt