Metadata-Version: 1.0
Name: package-test-2298
Version: 0.0.1
Summary: package testing
Home-page: http://nonono
Author: sheldon
Author-email: xing.gao@nokia.com
License: MIT Licence
Keywords: pip,datacanvas,eds,xiaoh
Platform: any
